{
  "authority": "validator-ast-and-corpus-source-inspection-only",
  "claimLimit": "Does not prove isolation for API, browser, provider, or future consumers.",
  "corpusDigest": "d3aa733d92dc17b9a360d968f8e6102326d632f45c527aa18055844ee50de84d",
  "evidenceClass": "fixture",
  "externalUrlHostCount": 0,
  "reportVersion": "1.0.0",
  "scannedAssetCount": 19,
  "validatorDynamicAccesses": 0,
  "validatorEnvironmentReads": 0,
  "validatorImportViolations": 0,
  "validatorNetworkCalls": 0,
  "validatorNetworkImports": 0,
  "validatorProcessImports": 0,
  "validatorPurityDerivedBy": "stdlib-ast-source-inspection",
  "validatorSocketImports": 0,
  "validatorSourceSha256": "3d55838eb20e55bb745c219c1da6684370784f638c145d43979e8008b202e668",
  "validatorSubprocessCalls": 0,
  "validatorWallClockOrWaitCalls": 0,
  "validatorWriteReferences": 0,
  "validatorWrites": 0
}
